{
  "id": "d7a8bdcb-b73b-42e6-81d7-5b3e5c170826",
  "prevId": "5406896c-4e50-467d-a6ab-95633383d6e0",
  "version": "5",
  "dialect": "pg",
  "tables": {
    "APIKey": {
      "name": "APIKey",
      "schema": "",
      "columns": {
        "keyId": {
          "name": "keyId",
          "type": "varchar(128)",
          "primaryKey": false,
          "notNull": true
        },
        "memId": {
          "name": "memId",
          "type": "varchar(128)",
          "primaryKey": false,
          "notNull": true
        },
        "hint": {
          "name": "hint",
          "type": "varchar(20)",
          "primaryKey": false,
          "notNull": true
        },
        "createdAt": {
          "name": "createdAt",
          "type": "timestamp (6) with time zone",
          "primaryKey": false,
          "notNull": true,
          "default": "now()"
        },
        "updatedAt": {
          "name": "updatedAt",
          "type": "timestamp (6) with time zone",
          "primaryKey": false,
          "notNull": true,
          "default": "now()"
        }
      },
      "indexes": {},
      "foreignKeys": {},
      "compositePrimaryKeys": {
        "APIKey_keyId_memId_pk": {
          "name": "APIKey_keyId_memId_pk",
          "columns": [
            "keyId",
            "memId"
          ]
        }
      },
      "uniqueConstraints": {}
    },
    "Attendance": {
      "name": "Attendance",
      "schema": "",
      "columns": {
        "id": {
          "name": "id",
          "type": "varchar(128)",
          "primaryKey": true,
          "notNull": true
        },
        "memId": {
          "name": "memId",
          "type": "varchar(128)",
          "primaryKey": false,
          "notNull": true
        },
        "eventId": {
          "name": "eventId",
          "type": "varchar(128)",
          "primaryKey": false,
          "notNull": true
        },
        "responseId": {
          "name": "responseId",
          "type": "varchar(128)",
          "primaryKey": false,
          "notNull": false
        },
        "createdAt": {
          "name": "createdAt",
          "type": "timestamp (6) with time zone",
          "primaryKey": false,
          "notNull": true,
          "default": "now()"
        },
        "updatedAt": {
          "name": "updatedAt",
          "type": "timestamp (6) with time zone",
          "primaryKey": false,
          "notNull": true,
          "default": "now()"
        }
      },
      "indexes": {},
      "foreignKeys": {},
      "compositePrimaryKeys": {},
      "uniqueConstraints": {}
    },
    "Event": {
      "name": "Event",
      "schema": "",
      "columns": {
        "id": {
          "name": "id",
          "type": "varchar(128)",
          "primaryKey": true,
          "notNull": true
        },
        "name": {
          "name": "name",
          "type": "varchar(191)",
          "primaryKey": false,
          "notNull": true
        },
        "start": {
          "name": "start",
          "type": "timestamp (6) with time zone",
          "primaryKey": false,
          "notNull": true
        },
        "end": {
          "name": "end",
          "type": "timestamp (6) with time zone",
          "primaryKey": false,
          "notNull": true
        },
        "description": {
          "name": "description",
          "type": "text",
          "primaryKey": false,
          "notNull": false
        },
        "image": {
          "name": "image",
          "type": "varchar(191)",
          "primaryKey": false,
          "notNull": false
        },
        "orgId": {
          "name": "orgId",
          "type": "varchar(128)",
          "primaryKey": false,
          "notNull": true
        },
        "formId": {
          "name": "formId",
          "type": "varchar(128)",
          "primaryKey": false,
          "notNull": false
        },
        "createdAt": {
          "name": "createdAt",
          "type": "timestamp (6) with time zone",
          "primaryKey": false,
          "notNull": true,
          "default": "now()"
        },
        "updatedAt": {
          "name": "updatedAt",
          "type": "timestamp (6) with time zone",
          "primaryKey": false,
          "notNull": true,
          "default": "now()"
        }
      },
      "indexes": {},
      "foreignKeys": {},
      "compositePrimaryKeys": {},
      "uniqueConstraints": {}
    },
    "FormResponse": {
      "name": "FormResponse",
      "schema": "",
      "columns": {
        "id": {
          "name": "id",
          "type": "varchar(128)",
          "primaryKey": true,
          "notNull": true
        },
        "formId": {
          "name": "formId",
          "type": "varchar(128)",
          "primaryKey": false,
          "notNull": true
        },
        "response": {
          "name": "response",
          "type": "json",
          "primaryKey": false,
          "notNull": true
        },
        "memId": {
          "name": "memId",
          "type": "varchar(128)",
          "primaryKey": false,
          "notNull": false
        },
        "createdAt": {
          "name": "createdAt",
          "type": "timestamp (6) with time zone",
          "primaryKey": false,
          "notNull": true,
          "default": "now()"
        },
        "updatedAt": {
          "name": "updatedAt",
          "type": "timestamp (6) with time zone",
          "primaryKey": false,
          "notNull": true,
          "default": "now()"
        }
      },
      "indexes": {},
      "foreignKeys": {},
      "compositePrimaryKeys": {},
      "uniqueConstraints": {}
    },
    "Member": {
      "name": "Member",
      "schema": "",
      "columns": {
        "id": {
          "name": "id",
          "type": "varchar(128)",
          "primaryKey": true,
          "notNull": true
        },
        "orgId": {
          "name": "orgId",
          "type": "varchar(128)",
          "primaryKey": false,
          "notNull": true
        },
        "userId": {
          "name": "userId",
          "type": "varchar(128)",
          "primaryKey": false,
          "notNull": true
        },
        "role": {
          "name": "role",
          "type": "role",
          "primaryKey": false,
          "notNull": true,
          "default": "'MEMBER'"
        },
        "additionalInfoId": {
          "name": "additionalInfoId",
          "type": "varchar(128)",
          "primaryKey": false,
          "notNull": false
        },
        "createdAt": {
          "name": "createdAt",
          "type": "timestamp (6) with time zone",
          "primaryKey": false,
          "notNull": true,
          "default": "now()"
        },
        "updatedAt": {
          "name": "updatedAt",
          "type": "timestamp (6) with time zone",
          "primaryKey": false,
          "notNull": true,
          "default": "now()"
        }
      },
      "indexes": {},
      "foreignKeys": {},
      "compositePrimaryKeys": {},
      "uniqueConstraints": {}
    },
    "Membership": {
      "name": "Membership",
      "schema": "",
      "columns": {
        "id": {
          "name": "id",
          "type": "varchar(128)",
          "primaryKey": true,
          "notNull": true
        },
        "memId": {
          "name": "memId",
          "type": "varchar(191)",
          "primaryKey": false,
          "notNull": true
        },
        "planId": {
          "name": "planId",
          "type": "varchar(191)",
          "primaryKey": false,
          "notNull": true
        },
        "decimal": {
          "name": "decimal",
          "type": "numeric",
          "primaryKey": false,
          "notNull": false
        },
        "provider": {
          "name": "provider",
          "type": "provider",
          "primaryKey": false,
          "notNull": true,
          "default": "'None'"
        },
        "createdAt": {
          "name": "createdAt",
          "type": "timestamp (6) with time zone",
          "primaryKey": false,
          "notNull": true,
          "default": "now()"
        },
        "updatedAt": {
          "name": "updatedAt",
          "type": "timestamp (6) with time zone",
          "primaryKey": false,
          "notNull": true,
          "default": "now()"
        }
      },
      "indexes": {},
      "foreignKeys": {},
      "compositePrimaryKeys": {},
      "uniqueConstraints": {}
    },
    "Organization": {
      "name": "Organization",
      "schema": "",
      "columns": {
        "id": {
          "name": "id",
          "type": "varchar(128)",
          "primaryKey": true,
          "notNull": true
        },
        "name": {
          "name": "name",
          "type": "varchar(191)",
          "primaryKey": false,
          "notNull": true
        },
        "createdAt": {
          "name": "createdAt",
          "type": "timestamp (6) with time zone",
          "primaryKey": false,
          "notNull": true,
          "default": "now()"
        },
        "updatedAt": {
          "name": "updatedAt",
          "type": "timestamp (6) with time zone",
          "primaryKey": false,
          "notNull": true,
          "default": "now()"
        }
      },
      "indexes": {},
      "foreignKeys": {},
      "compositePrimaryKeys": {},
      "uniqueConstraints": {}
    },
    "OrganizationForm": {
      "name": "OrganizationForm",
      "schema": "",
      "columns": {
        "id": {
          "name": "id",
          "type": "varchar(128)",
          "primaryKey": true,
          "notNull": true
        },
        "orgId": {
          "name": "orgId",
          "type": "varchar(191)",
          "primaryKey": false,
          "notNull": true
        },
        "name": {
          "name": "name",
          "type": "varchar(191)",
          "primaryKey": false,
          "notNull": true
        },
        "form": {
          "name": "form",
          "type": "json",
          "primaryKey": false,
          "notNull": true
        },
        "createdAt": {
          "name": "createdAt",
          "type": "timestamp (6) with time zone",
          "primaryKey": false,
          "notNull": true,
          "default": "now()"
        },
        "updatedAt": {
          "name": "updatedAt",
          "type": "timestamp (6) with time zone",
          "primaryKey": false,
          "notNull": true,
          "default": "now()"
        }
      },
      "indexes": {},
      "foreignKeys": {},
      "compositePrimaryKeys": {},
      "uniqueConstraints": {}
    },
    "plan": {
      "name": "plan",
      "schema": "",
      "columns": {
        "id": {
          "name": "id",
          "type": "varchar(128)",
          "primaryKey": true,
          "notNull": true
        },
        "orgId": {
          "name": "orgId",
          "type": "varchar(191)",
          "primaryKey": false,
          "notNull": true
        },
        "name": {
          "name": "name",
          "type": "varchar(191)",
          "primaryKey": false,
          "notNull": true
        },
        "start": {
          "name": "start",
          "type": "timestamp with time zone",
          "primaryKey": false,
          "notNull": false
        },
        "interval": {
          "name": "interval",
          "type": "bigint",
          "primaryKey": false,
          "notNull": false
        },
        "decimal": {
          "name": "decimal",
          "type": "numeric",
          "primaryKey": false,
          "notNull": false
        },
        "createdAt": {
          "name": "createdAt",
          "type": "timestamp (6) with time zone",
          "primaryKey": false,
          "notNull": true,
          "default": "now()"
        },
        "updatedAt": {
          "name": "updatedAt",
          "type": "timestamp (6) with time zone",
          "primaryKey": false,
          "notNull": true,
          "default": "now()"
        }
      },
      "indexes": {},
      "foreignKeys": {},
      "compositePrimaryKeys": {},
      "uniqueConstraints": {}
    },
    "User": {
      "name": "User",
      "schema": "",
      "columns": {
        "id": {
          "name": "id",
          "type": "varchar(128)",
          "primaryKey": true,
          "notNull": true
        },
        "firstName": {
          "name": "firstName",
          "type": "varchar(191)",
          "primaryKey": false,
          "notNull": false
        },
        "lastName": {
          "name": "lastName",
          "type": "varchar(191)",
          "primaryKey": false,
          "notNull": false
        },
        "email": {
          "name": "email",
          "type": "varchar(191)",
          "primaryKey": false,
          "notNull": true
        },
        "emailVerified": {
          "name": "emailVerified",
          "type": "boolean",
          "primaryKey": false,
          "notNull": true
        },
        "profilePictureUrl": {
          "name": "profilePictureUrl",
          "type": "varchar(191)",
          "primaryKey": false,
          "notNull": false
        },
        "createdAt": {
          "name": "createdAt",
          "type": "timestamp (6) with time zone",
          "primaryKey": false,
          "notNull": true,
          "default": "now()"
        },
        "updatedAt": {
          "name": "updatedAt",
          "type": "timestamp (6) with time zone",
          "primaryKey": false,
          "notNull": true,
          "default": "now()"
        }
      },
      "indexes": {},
      "foreignKeys": {},
      "compositePrimaryKeys": {},
      "uniqueConstraints": {
        "User_email_key": {
          "name": "User_email_key",
          "nullsNotDistinct": false,
          "columns": [
            "email"
          ]
        }
      }
    }
  },
  "enums": {
    "role": {
      "name": "role",
      "values": {
        "OWNER": "OWNER",
        "ADMIN": "ADMIN",
        "MEMBER": "MEMBER"
      }
    },
    "provider": {
      "name": "provider",
      "values": {
        "Jonze": "Jonze",
        "Cashapp": "Cashapp",
        "Zelle": "Zelle",
        "Venmo": "Venmo",
        "Other": "Other",
        "None": "None"
      }
    }
  },
  "schemas": {},
  "_meta": {
    "columns": {},
    "schemas": {},
    "tables": {}
  }
}